aiger_gridworld/__init__.py
aiger_gridworld/dynamics.py
aiger_gridworld/vis.py
py_aiger_gridworld-0.4.3.dist-info/LICENSE
py_aiger_gridworld-0.4.3.dist-info/METADATA
py_aiger_gridworld-0.4.3.dist-info/WHEEL
py_aiger_gridworld-0.4.3.dist-info/RECORD
