Metadata-Version: 2.1
Name: py-aiger-gridworld
Version: 0.4.3
Summary: Library for modeling gridworlds as AIGER circuits.
License: MIT
Author: Marcell Vazquez-Chanlatte
Author-email: mvc@linux.com
Requires-Python: >=3.9,<4.0
Classifier: License :: OSI Approved :: MIT License
Classifier: Programming Language :: Python :: 3
Classifier: Programming Language :: Python :: 3.9
Classifier: Programming Language :: Python :: 3.10
Classifier: Programming Language :: Python :: 3.11
Requires-Dist: bidict (>=0.22,<0.23)
Requires-Dist: funcy (>=1.13,<2.0)
Requires-Dist: py-aiger (>=6.0.0,<7.0.0)
Requires-Dist: py-aiger-bv (>=4.0.0,<5.0.0)
Requires-Dist: py-aiger-discrete (>=0.1.10,<0.2.0)
